tg_option_container/__init__.py
tg_option_container/container.py
tg_option_container/types.py
tg_option_container-0.4.0.dist-info/DESCRIPTION.rst
tg_option_container-0.4.0.dist-info/METADATA
tg_option_container-0.4.0.dist-info/RECORD
tg_option_container-0.4.0.dist-info/WHEEL
tg_option_container-0.4.0.dist-info/metadata.json
tg_option_container-0.4.0.dist-info/top_level.txt
