Metadata-Version: 2.0
Name: tg-option-container
Version: 0.4.0
Summary: Container for dictionary-like validated data structures
Home-page: https://github.com/thorgate/tg-option-container
Author: Thorgate
Author-email: code@thorgate.eu
License: BSD 3-Clause
Platform: UNKNOWN
Classifier: Development Status :: 3 - Alpha
Classifier: Environment :: Console
Classifier: Environment :: Web Environment
Classifier: Intended Audience :: Developers
Classifier: License :: OSI Approved :: BSD License
Classifier: Operating System :: OS Independent
Classifier: Programming Language :: Python
Classifier: Programming Language :: Python :: 2
Classifier: Programming Language :: Python :: 3
Requires-Dist: python-dateutil
Requires-Dist: six
